FileKit
