Metadata-Version: 2.1
Name: FileKit
Version: 1.0.7
Author: 孙亮
